bgframework/__init__.py
bgframework/add_ons.py
bgframework/admin.py
bgframework/ajax.py
bgframework/apps.py
bgframework/assets.py
bgframework/context_processors.py
bgframework/settings.py
bgframework/urls.py
bgframework/views.py
bgframework/classview/__init__.py
bgframework/classview/base.py
bgframework/conf/app_template/__init__.py-tpl
bgframework/conf/app_template/admin.py-tpl
bgframework/conf/app_template/apps.py-tpl
bgframework/conf/app_template/bgf_addons.py-tpl
bgframework/conf/app_template/models.py-tpl
bgframework/conf/app_template/tests.py-tpl
bgframework/conf/app_template/views.py-tpl
bgframework/conf/app_template/migrations/__init__.py-tpl
bgframework/management/__init__.py
bgframework/management/commands/__init__.py
bgframework/management/commands/startbgfapp.py
bgframework/migrations/__init__.py
bgframework/static/ajaxcsrftoken.js
bgframework/static/base.css
bgframework/static/bgframework.js
bgframework/static/ace2/ace-elements.js
bgframework/static/ace2/ace-extra.js
bgframework/static/ace2/ace-fonts.css
bgframework/static/ace2/ace-ie.css
bgframework/static/ace2/ace-part2.css
bgframework/static/ace2/ace-rtl.css
bgframework/static/ace2/ace-skins.css
bgframework/static/ace2/ace.css
bgframework/static/ace2/ace.js
bgframework/static/bgframework/packed.css
bgframework/static/bgframework/packed.js
bgframework/static/bgframework/images/avatar.jpg
bgframework/static/bgframework/images/twitter-avatar-minion.jpg
bgframework/static/bower/bootstrap/Gruntfile.js
bgframework/static/bower/bootstrap/components.html
bgframework/static/bower/bootstrap/css.html
bgframework/static/bower/bootstrap/customize.html
bgframework/static/bower/bootstrap/getting-started.html
bgframework/static/bower/bootstrap/index.html
bgframework/static/bower/bootstrap/javascript.html
bgframework/static/bower/bootstrap/package.js
bgframework/static/bower/bootstrap/_includes/ads.html
bgframework/static/bower/bootstrap/_includes/footer.html
bgframework-0.8.3.dist-info/DESCRIPTION.rst
bgframework-0.8.3.dist-info/METADATA
bgframework-0.8.3.dist-info/RECORD
bgframework-0.8.3.dist-info/WHEEL
bgframework-0.8.3.dist-info/metadata.json
bgframework-0.8.3.dist-info/pbr.json
bgframework-0.8.3.dist-info/top_level.txt
