Metadata-Version: 2.0
Name: bgframework
Version: 0.8.3
Summary: Django background management full-stack framework
Home-page: https://github.com/tkliuxing/bgframework
Author: Ronald White
Author-email: ouyanghongyu@gmail.com
License: MIT License
Platform: OS Independent
Classifier: Development Status :: 4 - Beta
Classifier: Environment :: Web Environment
Classifier: Framework :: Django
Classifier: Intended Audience :: Developers
Classifier: License :: OSI Approved :: MIT License
Classifier: Operating System :: OS Independent
Classifier: Programming Language :: Python
Classifier: Topic :: Communications
Classifier: Topic :: Internet :: WWW/HTTP :: Dynamic Content
Classifier: Topic :: Internet :: WWW/HTTP :: Dynamic Content :: Message Boards
Classifier: Topic :: Internet :: WWW/HTTP :: Site Management
Classifier: Programming Language :: Python :: 3.4
Requires-Dist: Django
Requires-Dist: django-bootstrap-form-tkliuxing
Requires-Dist: django-braces
Requires-Dist: django-sekizai
Requires-Dist: six (==1.10.0)
